pyb3_data_client/__init__.py
pyb3_data_client/client.py
pyb3_data_client/exceptions.py
pyb3_data_client/venv/lib/python3.14/site-packages/build/__init__.py
pyb3_data_client/venv/lib/python3.14/site-packages/build/__main__.py
pyb3_data_client/venv/lib/python3.14/site-packages/build/_builder.py
pyb3_data_client/venv/lib/python3.14/site-packages/build/_ctx.py
pyb3_data_client/venv/lib/python3.14/site-packages/build/_exceptions.py
pyb3_data_client/venv/lib/python3.14/site-packages/build/_types.py
pyb3_data_client/venv/lib/python3.14/site-packages/build/_util.py
pyb3_data_client/venv/lib/python3.14/site-packages/build/env.py
pyb3_data_client/venv/lib/python3.14/site-packages/build/util.py
pyb3_data_client/venv/lib/python3.14/site-packages/build/_compat/__init__.py
pyb3_data_client/venv/lib/python3.14/site-packages/build/_compat/importlib.py
pyb3_data_client/venv/lib/python3.14/site-packages/build/_compat/tarfile.py
pyb3_data_client/venv/lib/python3.14/site-packages/build/_compat/tomllib.py
pyb3_data_client/venv/lib/python3.14/site-packages/certifi/__init__.py
pyb3_data_client/venv/lib/python3.14/site-packages/certifi/__main__.py
pyb3_data_client/venv/lib/python3.14/site-packages/certifi/core.py
pyb3_data_client/venv/lib/python3.14/site-packages/charset_normalizer/__init__.py
pyb3_data_client/venv/lib/python3.14/site-packages/charset_normalizer/__main__.py
pyb3_data_client/venv/lib/python3.14/site-packages/charset_normalizer/api.py
pyb3_data_client/venv/lib/python3.14/site-packages/charset_normalizer/cd.py
pyb3_data_client/venv/lib/python3.14/site-packages/charset_normalizer/constant.py
pyb3_data_client/venv/lib/python3.14/site-packages/charset_normalizer/legacy.py
pyb3_data_client/venv/lib/python3.14/site-packages/charset_normalizer/md.py
pyb3_data_client/venv/lib/python3.14/site-packages/charset_normalizer/models.py
pyb3_data_client/venv/lib/python3.14/site-packages/charset_normalizer/utils.py
pyb3_data_client-1.0.0.dist-info/licenses/LICENSE
pyb3_data_client-1.0.0.dist-info/METADATA
pyb3_data_client-1.0.0.dist-info/WHEEL
pyb3_data_client-1.0.0.dist-info/top_level.txt
pyb3_data_client-1.0.0.dist-info/RECORD
