Metadata-Version: 2.4
Name: pyb3-data-client
Version: 1.0.0
Summary: Python client for B3 Market Data API
Home-page: https://github.com/PedroDnT/pyb3
Author: Pedro Todescan
Author-email: Pedro Todescan <pedrotodescan@gmail.com>
Maintainer-email: Pedro Todescan <pedrotodescan@gmail.com>
License: MIT
Project-URL: Homepage, https://github.com/PedroDnT/pyb3
Project-URL: Documentation, https://api.b3data.com/docs
Project-URL: Repository, https://github.com/PedroDnT/pyb3
Project-URL: Issues, https://github.com/PedroDnT/pyb3/issues
Project-URL: Changelog, https://github.com/PedroDnT/pyb3/blob/main/CHANGELOG.md
Keywords: b3,bovespa,stock,market,data,api,finance,brazil,pyb3
Classifier: Development Status :: 5 - Production/Stable
Classifier: Intended Audience :: Developers
Classifier: Intended Audience :: Financial and Insurance Industry
Classifier: Intended Audience :: Science/Research
Classifier: Operating System :: OS Independent
Classifier: Programming Language :: Python :: 3
Classifier: Programming Language :: Python :: 3.8
Classifier: Programming Language :: Python :: 3.9
Classifier: Programming Language :: Python :: 3.10
Classifier: Programming Language :: Python :: 3.11
Classifier: Programming Language :: Python :: 3.12
Classifier: Programming Language :: Python :: 3.13
Classifier: Topic :: Office/Business :: Financial
Classifier: Topic :: Scientific/Engineering
Classifier: Topic :: Software Development :: Libraries :: Python Modules
Requires-Python: >=3.8
License-File: LICENSE
Requires-Dist: requests>=2.31.0
Requires-Dist: polars>=0.20.0
Requires-Dist: pyarrow>=15.0.0
Provides-Extra: pandas
Requires-Dist: pandas>=2.0.0; extra == "pandas"
Provides-Extra: dev
Requires-Dist: pytest>=7.4.0; extra == "dev"
Requires-Dist: pytest-cov>=4.1.0; extra == "dev"
Requires-Dist: black>=24.0.0; extra == "dev"
Requires-Dist: ruff>=0.1.0; extra == "dev"
Dynamic: author
Dynamic: home-page
Dynamic: license-file
Dynamic: requires-python
